Metadata-Version: 2.1
Name: tom-education
Version: 1.1.9
Summary: TOM toolkit plugin for educational projects
Home-page: UNKNOWN
Author: Joe Singleton
Author-email: joesingo@gmail.com
Maintainer: Edward Gomez
Maintainer-email: egomez@lco.global
License: UNKNOWN
Platform: UNKNOWN
Requires-Dist: astropy
Requires-Dist: astroscrappy
Requires-Dist: tomtoolkit (>=1.4.0)
Requires-Dist: numpy
Requires-Dist: imageio-ffmpeg
Requires-Dist: imageio
Requires-Dist: django-dramatiq
Requires-Dist: dramatiq
Requires-Dist: redis
Requires-Dist: watchdog
Requires-Dist: watchdog-gevent
Requires-Dist: djangorestframework
Requires-Dist: fits2image (==0.4.3)
Requires-Dist: django-storages
Requires-Dist: boto3
Provides-Extra: test
Requires-Dist: factory-boy ; extra == 'test'
